README.md
iacoll.py
setup.py
iacoll.egg-info/PKG-INFO
iacoll.egg-info/SOURCES.txt
iacoll.egg-info/dependency_links.txt
iacoll.egg-info/entry_points.txt
iacoll.egg-info/requires.txt
iacoll.egg-info/top_level.txt