Metadata-Version: 2.1
Name: iacoll
Version: 0.0.3
Summary: Collect metadata for Internet Archive collections
Home-page: https://github.com/edsu/iacoll
Author: Ed Summers
Author-email: ehs@pobox.com
License: UNKNOWN
Platform: UNKNOWN
Requires-Python: >=3.6
